pytorch_lightning_cifar/__init__.py
pytorch_lightning_cifar/models/__init__.py
pytorch_lightning_cifar/models/densenet.py
pytorch_lightning_cifar/models/dla.py
pytorch_lightning_cifar/models/dla_simple.py
pytorch_lightning_cifar/models/dpn.py
pytorch_lightning_cifar/models/efficientnet.py
pytorch_lightning_cifar/models/googlenet.py
pytorch_lightning_cifar/models/lenet.py
pytorch_lightning_cifar/models/mobilenet.py
pytorch_lightning_cifar/models/mobilenetv2.py
pytorch_lightning_cifar/models/pnasnet.py
pytorch_lightning_cifar/models/preact_resnet.py
pytorch_lightning_cifar/models/regnet.py
pytorch_lightning_cifar/models/resnet.py
pytorch_lightning_cifar/models/resnext.py
pytorch_lightning_cifar/models/senet.py
pytorch_lightning_cifar/models/shufflenet.py
pytorch_lightning_cifar/models/shufflenetv2.py
pytorch_lightning_cifar/models/vgg.py
pytorch_lightning_cifar-0.1.5.dist-info/LICENSE
pytorch_lightning_cifar-0.1.5.dist-info/METADATA
pytorch_lightning_cifar-0.1.5.dist-info/WHEEL
pytorch_lightning_cifar-0.1.5.dist-info/top_level.txt
pytorch_lightning_cifar-0.1.5.dist-info/RECORD
