Metadata-Version: 2.1
Name: pytorch-lightning-cifar
Version: 0.1.5
Summary: Common CNN models defined for PyTorch Lightning 
Home-page: https://github.com/Wheest/pytorch-lightning-cifar.git
Author: Perry Gibson
Author-email: perry@gibsonic.org
License: MIT
Platform: UNKNOWN
License-File: LICENSE
Requires-Dist: torch (>=1.7.1)
Requires-Dist: pytorch-lightning
Requires-Dist: torchvision
Requires-Dist: lightning-bolts
